village_data_analysis/__init__.py
village_data_analysis/analyzer.py
village_data_analysis/coord_converter.py
village_data_analysis/data_create.py
village_data_analysis/helpers.py
village_data_analysis-1.5.dist-info/METADATA
village_data_analysis-1.5.dist-info/WHEEL
village_data_analysis-1.5.dist-info/top_level.txt
village_data_analysis-1.5.dist-info/RECORD
